LICENSE
README.md
setup.py
ShapeYModular.egg-info/PKG-INFO
ShapeYModular.egg-info/SOURCES.txt
ShapeYModular.egg-info/dependency_links.txt
ShapeYModular.egg-info/requires.txt
ShapeYModular.egg-info/top_level.txt
shapeymodular/__init__.py
shapeymodular/analysis/__init__.py
shapeymodular/analysis/nn_analysis.py
shapeymodular/analysis/postprocess.py
shapeymodular/analysis/preprocess.py
shapeymodular/data_classes/__init__.py
shapeymodular/data_classes/axis_description.py
shapeymodular/data_classes/corrmat.py
shapeymodular/data_classes/graph_data.py
shapeymodular/data_classes/nn_analysis_configs.py
shapeymodular/data_loader/__init__.py
shapeymodular/data_loader/data_loader.py
shapeymodular/data_loader/dir_mat.py
shapeymodular/data_loader/hdf.py
shapeymodular/data_loader/sampler.py
shapeymodular/macros/__init__.py
shapeymodular/macros/compute_distance.py
shapeymodular/macros/compute_distance_torch.py
shapeymodular/macros/compute_threshold.py
shapeymodular/macros/extract_features.py
shapeymodular/macros/graphing.py
shapeymodular/macros/nn_batch.py
shapeymodular/test/__init__.py
shapeymodular/test/conftest.py
shapeymodular/torchutils/__init__.py
shapeymodular/torchutils/distances.py
shapeymodular/torchutils/imageloader.py
shapeymodular/torchutils/modelutils.py
shapeymodular/utils/ShapeY200_objs.json
shapeymodular/utils/__init__.py
shapeymodular/utils/analysis_config_pw_cr.json
shapeymodular/utils/analysis_config_pw_no_cr.json
shapeymodular/utils/cmdtools.py
shapeymodular/utils/constants.py
shapeymodular/utils/features_imgnames_all.txt
shapeymodular/utils/features_imgnames_pw_series.txt
shapeymodular/utils/image_name_helper.py
shapeymodular/utils/imgnames_all.txt
shapeymodular/utils/imgnames_pw_series.txt
shapeymodular/utils/indexing_helper.py
shapeymodular/visualization/__init__.py
shapeymodular/visualization/correlation_fall_off.py
shapeymodular/visualization/exclusion_distance.py
shapeymodular/visualization/histogram.py
shapeymodular/visualization/image.py
shapeymodular/visualization/line_graph.py
shapeymodular/visualization/styles.py
shapeymodular/visualization/tuning_curve.py