Metadata-Version: 2.1
Name: ShapeYModular
Version: 2.0.5
Summary: Benchmark that tests shape recognition
Home-page: https://github.com/njw0709/ShapeYV2
Author: Jong Woo Nam
Author-email: namj@usc.edu
License: MIT
Keywords: tests shape recognition capacity
Classifier: License :: OSI Approved :: MIT License
Classifier: Programming Language :: Python :: 3.9
Classifier: Development Status :: 4 - Beta
License-File: LICENSE
